            {
            }
         ]
      {
      {
      {
      {
      {
      }
      }
      }
      }
      }
   ]
   ]
   ]
   ]
   }
{
}
   "agenda" : [
   "all_day" : false
         "classification" : []
   "classification" : "event"
      "coordinates" : null
         "date" : ""
   "description" : ""
         "description" : "See Land Use Calendar"
   "documents" : [
   "end_date" : ""
         "entity_type" : "organization"
         "extras" : {}
   "extras" : {}
         "links" : [
   "links" : []
   "location" : {
         "media" : []
   "media" : []
               "media_type" : "application/pdf"
      "name" : "Council Chambers - City Hall"
         "name" : "Subcommittee on Zoning and Franchises"
   "name" : "Subcommittee on Zoning and Franchises"
      "note" : ""
         "note" : "Agenda"
         "note" : "api"
         "note" : "participant"
         "notes" : []
         "note" : "web"
         "order" : "0"
         "organization_id" : "~{\"name\": \"Subcommittee on Zoning and Franchises\"}"
   "participants" : [
   "pupa_id" : "17722"
         "related_entities" : []
   "sources" : [
   "start_date" : "2020-05-12T14:00:00+00:00"
   "status" : "confirmed"
         "subjects" : []
               "text" : ""
         "url" : "https://legistar.council.nyc.gov/MeetingDetail.aspx?ID=749824&GUID=C6514EC7-4B5A-4D34-A689-7D10205880E2&Options=info&Search="
               "url" : "https://legistar.council.nyc.gov/View.ashx?M=A&ID=749824&GUID=C6514EC7-4B5A-4D34-A689-7D10205880E2"
         "url" : "https://webapi.legistar.com/v1/nyc/events/17722"
