            {
            {
            {
            {
            {
            }
            }
            }
            }
            }
         ]
         ]
         ]
         ]
         ]
      {
      {
      {
      {
      {
      {
      {
      {
      }
      }
      }
      }
      }
      }
      }
      }
   ]
   ]
   ]
   ]
   ]
   }
   }
{
}
   "agenda" : [
   "all_day" : false
               "bill_id" : "~{\"identifier\": \"Int 1947-2020\"}"
               "bill_id" : "~{\"identifier\": \"Int 2072-2020\"}"
         "classification" : []
         "classification" : []
   "classification" : "event"
      "coordinates" : null
         "date" : ""
         "date" : ""
         "date" : ""
   "description" : ""
         "description" : "A Local Law to amend the administrative code of the city of New York in relation to greenhouse gas emissions reduction methods and outreach and education"
         "description" : "A Local Law to amend the administrative code of the city of New York in relation to rent regulated accommodations"
   "documents" : [
   "end_date" : ""
               "entity_type" : "bill"
               "entity_type" : "bill"
         "entity_type" : "organization"
         "extras" : {}
         "extras" : {}
   "extras" : {
         "links" : [
         "links" : [
         "links" : [
   "links" : []
   "location" : {
      "location note" : "VOTE"
         "media" : []
         "media" : []
   "media" : [
               "media_type" : "application/pdf"
               "media_type" : "application/pdf"
               "media_type" : "text/html"
         "name" : "Committee on Environmental Protection"
   "name" : "Committee on Environmental Protection"
               "name" : "Int 1947-2020"
               "name" : "Int 2072-2020"
      "name" : "REMOTE HEARING (VIRTUAL ROOM 1)"
      "note" : ""
         "note" : "Agenda"
         "note" : "api"
               "note" : "consideration"
               "note" : "consideration"
         "note" : "Minutes"
         "note" : "participant"
         "note" : "Recording"
         "notes" : []
         "notes" : []
         "note" : "web"
         "order" : "0"
         "order" : "1"
         "organization_id" : "~{\"name\": \"Committee on Environmental Protection\"}"
   "participants" : [
   "pupa_id" : "18236"
         "related_entities" : [
         "related_entities" : [
   "sources" : [
   "start_date" : "2020-10-29T14:30:00+00:00"
   "status" : "passed"
         "subjects" : []
         "subjects" : []
               "text" : ""
               "text" : ""
               "text" : ""
         "url" : "https://legistar.council.nyc.gov/MeetingDetail.aspx?ID=812512&GUID=9C9C5456-AB13-4CA0-B247-F78C15ACFDF9&Options=info|&Search="
               "url" : "https://legistar.council.nyc.gov//Video.aspx?Mode=Auto&URL=aHR0cHM6Ly9jb3VuY2lsbnljLnZpZWJpdC5jb20vdm9kLz9zPXRydWUmdj1OWUNDLVJFTU9URS1FUC0xMDI5MjAyMC5tcDQ%3d&Mode2=Video"
               "url" : "https://legistar.council.nyc.gov/View.ashx?M=A&ID=812512&GUID=9C9C5456-AB13-4CA0-B247-F78C15ACFDF9"
               "url" : "https://legistar.council.nyc.gov/View.ashx?M=M&ID=812512&GUID=9C9C5456-AB13-4CA0-B247-F78C15ACFDF9"
         "url" : "https://webapi.legistar.com/v1/nyc/events/18236"
