            {
            }
         ]
      {
      {
      {
      {
      {
      }
      }
      }
      }
      }
   ]
   ]
   ]
   }
{
}
   "agenda" : [
   "all_day" : false
         "classification" : []
         "classification" : []
   "classification" : "event"
      "coordinates" : null
         "date" : ""
   "description" : ""
         "description" : "Agenda – 1:30 p.m."
         "description" : "Ceremonial Tributes – 1:00 p.m."
   "documents" : [
   "end_date" : ""
         "extras" : {}
         "extras" : {}
   "extras" : {}
         "links" : [
   "links" : []
   "location" : {
         "media" : []
         "media" : []
   "media" : []
               "media_type" : "application/pdf"
   "name" : "City Council"
      "name" : "Council Chambers - City Hall"
      "note" : ""
         "note" : "Agenda"
         "note" : "api"
         "notes" : []
         "notes" : []
         "note" : "web"
         "order" : "0"
         "order" : "1"
   "participants" : []
   "pupa_id" : "17683"
         "related_entities" : []
         "related_entities" : []
   "sources" : [
   "start_date" : "2020-05-20T17:30:00+00:00"
   "status" : "confirmed"
         "subjects" : []
         "subjects" : []
               "text" : ""
         "url" : "https://legistar.council.nyc.gov/MeetingDetail.aspx?ID=746788&GUID=7680C52E-8BD3-45DD-B482-A93AACD81303&Options=info&Search="
               "url" : "https://legistar.council.nyc.gov/View.ashx?M=A&ID=746788&GUID=7680C52E-8BD3-45DD-B482-A93AACD81303"
         "url" : "https://webapi.legistar.com/v1/nyc/events/17683"
